smdanalysis/__init__.py
smdanalysis/__main__.py
smdanalysis/eventdetector.py
smdanalysis/eventsinfo.py
smdanalysis/mainwindow.py
smdanalysis/setup.py
smdanalysis/timeseries.py
smdanalysis/wavelet.py
smdana-0.1.0.dist-info/METADATA
smdana-0.1.0.dist-info/WHEEL
smdana-0.1.0.dist-info/licenses/LICENSE
smdana-0.1.0.dist-info/RECORD
